{
  "news_paper": "ElTerritorio",
  "section": "País y Mund ",
  "title": "La justicia laboral declaró la invalidez de seis artículos del DNU de Milei",
  "link": "https://www.elterritorio.com.ar/noticias/2024/01/24/817943-la-justicia-laboral-declaro-la-invalidez-de-seis-articulos-del-dnu-de-milei",
  "summary": "La jueza laboral de feria Liliana Rodríguez Fernández hizo \"parcialmente lugar a la acción de amparo\" de la Confederación General del Trabajo (CGT) contra el Gobierno",
  "published": "Thu, 25 Jan 2024 00:13:49 GMT",
  "tags": "",
  "credit": ""
}