{
  "news_paper": "Perfil",
  "section": "Opinión",
  "title": "Milei: ni dictadura ni democracia representativa",
  "link": "https://www.perfil.com/noticias/elobservador/milei-ni-dictadura-ni-democracia-representativa.phtml",
  "summary": "<p><img alt=\"2023_01_20_milei_cedoc_g\" src=\"https://fotos.perfil.com/2024/01/20/trim/540/304/20230120mileicedocg-1741170.jpg\" /></p>Argentina vivió décadas de atropellos institucionales de parte del kirchnerismo, dice la autora. La nueva gestión parece decidida con convicción a repetir la historia. <a href=\"https://www.perfil.com/noticias/elobservador/milei-ni-dictadura-ni-democracia-representativa.phtml\">Leer más</a>",
  "published": "Sat, 20 Jan 2024 06:50:16 GMT",
  "tags": "",
  "credit": ""
}{
  "news_paper": "Perfil",
  "section": "Opinión",
  "title": "La parábola espectacularmente perfecta de Milei",
  "link": "https://www.perfil.com/noticias/opinion/la-parabola-espectacularmente-perfecta-de-milei.phtml",
  "summary": "<p><img alt=\"macri milei 25012024\" src=\"https://fotos.perfil.com/2024/01/25/trim/540/304/macri-milei-25012024-1744517.jpg\" /></p>Milei: producto exitoso de Massa para debilitar a Mauricio (que terminó asociado con Mauricio para vencer a Massa). <a href=\"https://www.perfil.com/noticias/opinion/la-parabola-espectacularmente-perfecta-de-milei.phtml\">Leer más</a>",
  "published": "Thu, 25 Jan 2024 21:28:02 GMT",
  "tags": "",
  "credit": ""
}