{
  "news_paper": "diariocronica",
  "section": "Actualidad ",
  "title": "Milei visitó Vaca Muerta y se reunió con los principales empresarios del sector energético",
  "link": "https://www.diariocronica.com.ar/noticias/2024/08/08/100448-milei-visito-vaca-muerta-y-se-reunio-con-los-principales-empresarios-del-sector-energetico",
  "summary": "",
  "published": "Thu, 08 Aug 2024 19:54:45 GMT",
  "tags": "",
  "credit": ""
}{
  "news_paper": "diariocronica",
  "section": "Actualidad ",
  "title": "Milei visitó Vaca Muerta y se reunió con los principales empresarios del sector energético",
  "link": "https://www.diariocronica.com.ar/noticias/2024/08/08/100448-milei-visito-vaca-muerta-y-se-reunio-con-los-principales-empresarios-del-sector-energetico",
  "summary": "",
  "published": "Thu, 08 Aug 2024 19:54:45 GMT",
  "tags": "",
  "credit": ""
}