{
  "news_paper": "BigBangNews",
  "section": "Actualidad",
  "title": "Quién fue la condesa María Eugenia de Chikoff: el detrás de la chicana de CFK a Milei por sus \"modos\"",
  "link": "https://www.bigbangnews.com/actualidad/quien-fue-condesa-maria-eugenia-chikoff-detras-chicana-cfk-milei-sus-modos-n89739",
  "summary": "<img src=\"https://statics.bigbangnews.com/2024/04/crop/662d7ffdd42a0__993x610.webp\" /><p>La ex presidenta cruzó al libertario por sus declaraciones fuera de lugar y sus modos violentos.</p>",
  "published": "Sat, 27 Apr 2024 19:39:00 -0300",
  "tags": [
    {
      "term": "Actualidad",
      "scheme": null,
      "label": null
    }
  ],
  "credit": ""
}{
  "news_paper": "BigBangNews",
  "section": "Actualidad",
  "title": "¡Siga, siga el baile de Milei!: nafta, subte, trenes y celulares, los aumentos que se vienen en mayo",
  "link": "https://www.bigbangnews.com/actualidad/siga-siga-baile-milei-nafta-subte-trenes-celulares-aumentos-vienen-mayo-n89749",
  "summary": "<img src=\"https://statics.bigbangnews.com/2023/05/crop/a7279e8525e662753e8a31e63d7b11ae__993x610.webp\" /><p>Como desde hace cinco meses, todo sube y mayo no será la excepción.</p>",
  "published": "Mon, 29 Apr 2024 11:18:00 -0300",
  "tags": [
    {
      "term": "Actualidad",
      "scheme": null,
      "label": null
    }
  ],
  "credit": ""
}{
  "news_paper": "BigBangNews",
  "section": "Actualidad",
  "title": "¡Siga, siga el baile de Milei!: nafta, subte, trenes y celulares, los aumentos que se vienen en mayo",
  "link": "https://www.bigbangnews.com/actualidad/siga-siga-baile-milei-nafta-subte-trenes-celulares-aumentos-vienen-mayo-n89749",
  "summary": "<img src=\"https://statics.bigbangnews.com/2023/05/crop/a7279e8525e662753e8a31e63d7b11ae__993x610.webp\" /><p>Como desde hace cinco meses, todo sube y mayo no será la excepción.</p>",
  "published": "Mon, 29 Apr 2024 11:18:00 -0300",
  "tags": [
    {
      "term": "Actualidad",
      "scheme": null,
      "label": null
    }
  ],
  "credit": ""
}{
  "news_paper": "BigBangNews",
  "section": "Actualidad",
  "title": "¡Siga, siga el baile de Milei!: nafta, subte, trenes y celulares, los aumentos que se vienen en mayo",
  "link": "https://www.bigbangnews.com/actualidad/siga-siga-baile-milei-nafta-subte-trenes-celulares-aumentos-vienen-mayo-n89749",
  "summary": "<img src=\"https://statics.bigbangnews.com/2023/05/crop/a7279e8525e662753e8a31e63d7b11ae__993x610.webp\" /><p>Como desde hace cinco meses, todo sube y mayo no será la excepción.</p>",
  "published": "Mon, 29 Apr 2024 11:18:00 -0300",
  "tags": [
    {
      "term": "Actualidad",
      "scheme": null,
      "label": null
    }
  ],
  "credit": ""
}