{
  "news_paper": "AgenciaTélam",
  "section": "ÚltimasNoticias",
  "title": "Milei agradeció un mensaje del magnate Elon Musk, que elogió su discurso en Davos",
  "link": "https://www.telam.com.ar/notas/202401/652842-milei-musk.html",
  "summary": "\"Buena explicación de lo que hace que los países sean más o menos prósperos\", escribió el empresario sudafricano respecto a las palabras pronunciadas por el Presidente en el Foro Económico Mundial realizado en Suiza.",
  "published": "Thu, 18 Jan 2024 08:20:00 -0300",
  "tags": "",
  "credit": ""
}