{
  "news_paper": "Pagina12",
  "section": "ElPaís",
  "title": "Cristina Kirchner desafió a Caputo y a Milei a que digan la verdad sobre lo que están haciendo con los dólares",
  "link": "https://www.pagina12.com.ar/751841-cristina-kirchner-desafio-a-caputo-y-a-milei-a-que-digan-la-",
  "summary": "\"Deje de volver locos a sus seguidores y dígales la verdad de la milanesa\", le reclamó Cristina Kirchner al Presidente, después de que el Gobierno diera a conocer nuevas medidas para enfrentar la disparada del blue y los dólares financieros.",
  "published": "Sat, 13 Jul 2024 20:20:55 GMT",
  "tags": "",
  "credit": ""
}{
  "news_paper": "Pagina12",
  "section": "ElPaís",
  "title": "La danza del gato y el león: el enojo de Macri y los elogios forzados de Milei",
  "link": "https://www.pagina12.com.ar/751859-la-danza-del-gato-y-el-leon-el-enojo-de-macri-y-los-elogios-",
  "summary": "La frialdad en el Pacto de Mayo, los reproches del líder del PRO y la respuesta del Presidente. Tironeos de cara a las elecciones del año que viene.",
  "published": "Sat, 13 Jul 2024 22:17:15 GMT",
  "tags": "",
  "credit": ""
}