{
  "news_paper": "Pagina12",
  "section": "ElPaís",
  "title": "Mientras Javier Milei visita Estados Unidos, el Gobierno acumula renuncias",
  "link": "https://www.pagina12.com.ar/741086-mientras-javier-milei-visita-estados-unidos-el-gobierno-acum",
  "summary": "Guillermo Francos jurará el lunes cuando el mandatario a la Argentina. Todavía falta definir qué pasará con Federico Sturzenegger y el candidato a titular de AFI, Sergio Neiffert.",
  "published": "Fri, 31 May 2024 03:01:00 GMT",
  "tags": "",
  "credit": ""
}{
  "news_paper": "Pagina12",
  "section": "ElPaís",
  "title": "Mientras Javier Milei visita Estados Unidos, el Gobierno acumula renuncias",
  "link": "https://www.pagina12.com.ar/741086-mientras-javier-milei-visita-estados-unidos-el-gobierno-acum",
  "summary": "Guillermo Francos jurará el lunes cuando el mandatario a la Argentina. Todavía falta definir qué pasará con Federico Sturzenegger y el candidato a titular de AFI, Sergio Neiffert.",
  "published": "Fri, 31 May 2024 03:01:00 GMT",
  "tags": "",
  "credit": ""
}