{
  "news_paper": "Pagina12",
  "section": "ElPaís",
  "title": "La furia de Milei no tiene límites: ahora insultó a López Murphy y Melconian",
  "link": "https://www.pagina12.com.ar/748749-la-furia-de-milei-no-tiene-limites-ahora-insulto-a-lopez-mur",
  "summary": "\"Fracasado\", \"resentido\", \"cuatro de copas\", son algunos de los calificativos que utilizó Javier Milei contra los otros dos economistas neoliberales. El comunicado de los diputados del bloque Hacemos Coalición Federal.",
  "published": "Tue, 02 Jul 2024 03:01:00 GMT",
  "tags": "",
  "credit": ""
}{
  "news_paper": "Pagina12",
  "section": "ElPaís",
  "title": "La promesa de Milei, la explicación de Caputo y los dardos solapados de Sturzenegger",
  "link": "https://www.pagina12.com.ar/749154-la-promesa-de-milei-la-explicacion-de-caputo-y-los-dardos-so",
  "summary": "El Presidente buscó llevar calma a sus funcionarios frente a la escalada del dólar. Junto a Caputo, descartó una devaluación y prometió sostener el rumbo económico. El análisis de la Casa Rosada y las críticas internas al ministro.",
  "published": "Wed, 03 Jul 2024 02:32:59 GMT",
  "tags": "",
  "credit": ""
}