{
  "news_paper": "Pagina12",
  "section": "ElPaís",
  "title": "El doble juego de Macri con Milei no terminó",
  "link": "https://www.pagina12.com.ar/767517-el-doble-juego-de-macri-con-milei-no-termino",
  "summary": "El líder del PRO utiliza a sus alfiles parlamentarios para condicionar al Gobierno. El apoyo al veto presidencial, el rechazo a los fondos de la SIDE y la pelea por el mismo electorado.",
  "published": "Sun, 15 Sep 2024 03:01:00 GMT",
  "tags": "",
  "credit": "Archivo"
}{
  "news_paper": "Pagina12",
  "section": "ElPaís",
  "title": "Milei también quiere quedarse con la DAIA",
  "link": "https://www.pagina12.com.ar/767669-milei-tambien-quiere-quedarse-con-la-daia",
  "summary": "El financista y asesor del presidente, Darío Epstein, se presentó hace un mes como candidato para las elecciones claves de la entidad en Buenos Aires. Sin antecedentes en la vida comunitaria su aval más importante es el respaldo de la Rosada. Como Milei, también dice tener respaldo de la corriente ortodoxa Jabad Lubavitch aunque sus contrincantes también dicen lo mismo. La interna, el apoyo de Bullrich, Israel y Netanyahu.",
  "published": "Sun, 15 Sep 2024 21:32:13 GMT",
  "tags": "",
  "credit": "Archivo"
}