{
  "news_paper": "Pagina12",
  "section": "Economía",
  "title": "El dólar le encontró el punto débil a Milei",
  "link": "https://www.pagina12.com.ar/739244-el-dolar-le-encontro-el-punto-debil-a-milei",
  "summary": "La Mesa de Enlace avisó que la venta de granos es la menor en 6 años y presiona para devaluar. El mercado huele falta de reservas y debilidad política del Gobierno para sacar leyes clave. Un Caputo obligado a perder divisas para intentar frenar la mini corrida y el miedo a que el billete verde le ponga de inmediato un piso a la baja inflacionaria.",
  "published": "Fri, 24 May 2024 03:01:00 GMT",
  "tags": "",
  "credit": "Verónica Bellomo"
}{
  "news_paper": "Pagina12",
  "section": "Economía",
  "title": "Para Milei la disparada de los dólares no es un corrida cambiaria",
  "link": "https://www.pagina12.com.ar/739544-para-milei-la-disparada-de-los-dolares-no-es-un-corrida-camb",
  "summary": "Contra casi todos los análisis del mercado financiero, el Presidente minimiza el alza de las cotizaciones de los dólares financieros y el blue. Con el objetivo de tranquilizar a los especuladores adelanta que pronto va a terminar con las restricciones cambiarias.",
  "published": "Fri, 24 May 2024 22:03:08 GMT",
  "tags": "",
  "credit": "Carolina Camps"
}