{
  "news_paper": "BigBangNews",
  "section": "Política",
  "title": "La traición a la memoria de los héroes: Milei y su elogió a la responsable de la guerra de Malvinas",
  "link": "https://www.bigbangnews.com/politica/la-traicion-memoria-heroes-milei-su-elogio-responsable-guerra-malvinas-n89920",
  "summary": "<img src=\"https://statics.bigbangnews.com/2024/05/crop/663d2e085e761__993x610.webp\" /><p>Para el presidente, la \"dama de hierro\" fue \"brillante\".</p>",
  "published": "Thu, 09 May 2024 16:30:00 -0300",
  "tags": [
    {
      "term": "Política",
      "scheme": null,
      "label": null
    }
  ],
  "credit": ""
}{
  "news_paper": "BigBangNews",
  "section": "Política",
  "title": "\"Toto\" Caputo tendría sus horas contadas: Javier Milei estaría buscando reemplazarlo",
  "link": "https://www.bigbangnews.com/politica/toto-caputo-tendria-sus-horas-contadas-javier-milei-estaria-buscando-reemplazarlo-n89946",
  "summary": "<img src=\"https://statics.bigbangnews.com/2024/05/crop/663e84f691a69__993x610.webp\" /><p>Desde los problemas con China y Emiratos árabes al conflicto con las centrales eléctricas.</p>",
  "published": "Fri, 10 May 2024 17:30:00 -0300",
  "tags": [
    {
      "term": "Política",
      "scheme": null,
      "label": null
    }
  ],
  "credit": ""
}