{
  "news_paper": "BigBangNews",
  "section": "Política",
  "title": "Javier Milei trató de \"farsante mentiroso\" a Marcelo Longobardi y estalló contra FOPEA",
  "link": "https://www.bigbangnews.com/politica/javier-milei-trato-farsante-mentiroso-marcelo-longobardi-estallo-fopea-n92310",
  "summary": "<img src=\"https://statics.bigbangnews.com/2024/10/crop/670d621c4fe74__993x610.webp\" /><p>El periodista recibió una oleada de hate por expresar una opinión contraria al del oficialismo.</p>",
  "published": "Mon, 14 Oct 2024 15:16:00 -0300",
  "tags": [
    {
      "term": "Política",
      "scheme": null,
      "label": null
    }
  ],
  "credit": ""
}