{
  "news_paper": "BigBangNews",
  "section": "Política",
  "title": "Chau motosierra, ¿hola bisturí? Economistas proyectan cómo serán los próximos meses de Milei",
  "link": "https://www.bigbangnews.com/politica/chau-motosierra-hola-bisturi-economistas-proyectan-como-seran-proximos-meses-milei-n89955",
  "summary": "<img src=\"https://statics.bigbangnews.com/2024/02/crop/65d8b8fba8de0__993x610.webp\" /><p>Esperan una inflación entre el 4 y 6%, al tiempo que advierten: \"Ya no le queda más nada por licuar\".</p>",
  "published": "Sun, 12 May 2024 11:03:00 -0300",
  "tags": [
    {
      "term": "Política",
      "scheme": null,
      "label": null
    }
  ],
  "credit": ""
}{
  "news_paper": "BigBangNews",
  "section": "Política",
  "title": "Chau motosierra, ¿hola bisturí? Economistas proyectan cómo serán los próximos meses de Milei",
  "link": "https://www.bigbangnews.com/politica/chau-motosierra-hola-bisturi-economistas-proyectan-como-seran-proximos-meses-milei-n89955",
  "summary": "<img src=\"https://statics.bigbangnews.com/2024/02/crop/65d8b8fba8de0__993x610.webp\" /><p>Esperan una inflación entre el 4 y 6%, al tiempo que advierten: \"Ya no le queda más nada por licuar\".</p>",
  "published": "Sun, 12 May 2024 11:03:00 -0300",
  "tags": [
    {
      "term": "Política",
      "scheme": null,
      "label": null
    }
  ],
  "credit": ""
}