{
  "news_paper": "Pagina12",
  "section": "Sociedad",
  "title": "Milei, las mujeres y la moratoria previsional",
  "link": "https://www.pagina12.com.ar/732824-milei-las-mujeres-y-la-moratoria-previsional",
  "summary": "",
  "published": "Mon, 29 Apr 2024 22:57:58 GMT",
  "tags": "",
  "credit": ""
}{
  "news_paper": "Pagina12",
  "section": "Sociedad",
  "title": "Milei, las mujeres y la moratoria previsional",
  "link": "https://www.pagina12.com.ar/732824-milei-las-mujeres-y-la-moratoria-previsional",
  "summary": "",
  "published": "Mon, 29 Apr 2024 22:57:58 GMT",
  "tags": "",
  "credit": ""
}