{
  "news_paper": "ElPaís",
  "section": "Ediciones -Argentina",
  "title": "Milei, en el Foro Madrid en Buenos Aires: “Estoy haciendo el mejor Gobierno de la historia argentina”",
  "link": "https://elpais.com/argentina/2024-09-05/milei-en-el-foro-madrid-en-buenos-aires-estoy-haciendo-el-mejor-gobierno-de-la-historia-argentina.html",
  "summary": "El presidente es la estrella de un nuevo encuentro de las fuerzas de la ultraderecha organizado por Vox y la Fundación Disenso",
  "published": "Thu, 05 Sep 2024 17:19:22 GMT",
  "tags": [
    {
      "term": "Argentina",
      "scheme": null,
      "label": null
    },
    {
      "term": "América",
      "scheme": null,
      "label": null
    },
    {
      "term": "Latinoamérica",
      "scheme": null,
      "label": null
    },
    {
      "term": "Javier Milei",
      "scheme": null,
      "label": null
    },
    {
      "term": "Santiago Abascal",
      "scheme": null,
      "label": null
    },
    {
      "term": "La Libertad Avanza",
      "scheme": null,
      "label": null
    },
    {
      "term": "Vox",
      "scheme": null,
      "label": null
    },
    {
      "term": "Ultraderecha",
      "scheme": null,
      "label": null
    },
    {
      "term": "Partidos políticos",
      "scheme": null,
      "label": null
    },
    {
      "term": "Brasil",
      "scheme": null,
      "label": null
    },
    {
      "term": "Venezuela",
      "scheme": null,
      "label": null
    },
    {
      "term": "Elecciones Venezuela",
      "scheme": null,
      "label": null
    },
    {
      "term": "Jair Bolsonaro",
      "scheme": null,
      "label": null
    },
    {
      "term": "Nicolás Maduro",
      "scheme": null,
      "label": null
    },
    {
      "term": "Fraude electoral",
      "scheme": null,
      "label": null
    }
  ],
  "credit": "EPV"
}