{
  "news_paper": "lapoliticaonline",
  "section": " Economía",
  "title": "Milei cruzó a los economistas que dicen que el dólar está barato: \"Son unos chantas\"",
  "link": "https://www.lapoliticaonline.com/economia/milei-arremetio-contra-los-economistas-que-advierten-que-el-dolar-esta-barato-son-unos-chantas/",
  "summary": "En un encuentro con empresarios rechazó devaluar y defendió la continuidad del cepo.",
  "published": "Wed, 15 May 2024 19:54:49 GMT",
  "tags": "",
  "credit": ""
}{
  "news_paper": "lapoliticaonline",
  "section": " Economía",
  "title": "Milei cruzó a los economistas que dicen que el dólar está barato: \"Son unos chantas\"",
  "link": "https://www.lapoliticaonline.com/economia/milei-arremetio-contra-los-economistas-que-advierten-que-el-dolar-esta-barato-son-unos-chantas/",
  "summary": "En un encuentro con empresarios rechazó devaluar y defendió la continuidad del cepo.",
  "published": "Wed, 15 May 2024 19:54:49 GMT",
  "tags": "",
  "credit": ""
}{
  "news_paper": "lapoliticaonline",
  "section": " Economía",
  "title": "Bienvenido al pragmatismo: Milei anuncia que empezará a gastar, porque ya ajustó por demás",
  "link": "https://www.lapoliticaonline.com/economia/milei-reconoce-que-se-sobregiro-con-la-meta-fiscal-y-da-un-giro-kirchnerista/",
  "summary": "\"Si, sobre reaccionamos el equilibrio fiscal, pero ahora podemos empezar a gastar y devolver\", afirmó ante empresarios. El Ahora 12 se suma a otras medidas kirchneristas. La opinión de los economistas.",
  "published": "Fri, 17 May 2024 21:55:58 GMT",
  "tags": "",
  "credit": ""
}