{
  "news_paper": "AmbitoFinanciero",
  "section": "Negocios",
  "title": "Javier Milei se reunió con Nayib Bukele luego de que asuma su segundo mandato en El Salvador",
  "link": "https://www.ambito.com/politica/gira-presidencial-javier-milei-ya-esta-el-salvador-la-jura-presidencial-nayud-bukele-n6008250",
  "summary": "<p class=\"ignore-parser\">Luego de su encuentro con líderes tecnológicos en Estados Unidos, el Presidente viajó a El Salvador. Regresa a la Argentina este sábado.</p>",
  "published": "Sat, 01 Jun 2024 15:08:00 -0300",
  "tags": "",
  "credit": ""
}