{
  "news_paper": "AmbitoFinanciero",
  "section": "Negocios",
  "title": "La dura crítica de Mirtha Legrand a Javier Milei: \"Me da pena, me da miedo\"",
  "link": "https://www.ambito.com/espectaculos/la-dura-critica-mirtha-legrand-javier-milei-me-da-pena-me-da-miedo-n6059966",
  "summary": "<p class=\"ignore-parser\">La \"Chiqui\" cuestionó al Gobierno por los recientes acontecimientos en el Congreso donde hubo represión a jubilados por el veto de la reforma previsional. Hubo críticas en la mesaza al ataque con gas pimienta de la policía a una niña de 10 años.</p>",
  "published": "Sun, 15 Sep 2024 11:13:18 -0300",
  "tags": "",
  "credit": ""
}{
  "news_paper": "AmbitoFinanciero",
  "section": "Negocios",
  "title": "Fuerte operativo de seguridad en el Congreso esperando la llegada de Javier Milei",
  "link": "https://www.ambito.com/politica/fuerte-operativo-seguridad-el-congreso-esperando-la-llegada-javier-milei-n6060098",
  "summary": "<p class=\"ignore-parser\">Se espera que el mandatario ingrese al Palacio Legislativo pasadas las 20:40 para comenzar la presentación del Presupuesto 2025 a las 21.</p>",
  "published": "Sun, 15 Sep 2024 20:35:46 -0300",
  "tags": "",
  "credit": ""
}