{
  "news_paper": "AlJazeera",
  "section": "random",
  "title": "Defying protesters, Argentina’s Milei shoots down university funding plan",
  "link": "https://www.aljazeera.com/news/2024/10/3/defying-protesters-argentinas-milei-shoots-down-university-funding-plan?traffic_source=rss",
  "summary": "Milei vetoed a law that would guarantee funding for free public universities, angering students and educators.",
  "published": "Thu, 03 Oct 2024 15:57:28 +0000",
  "tags": [
    {
      "term": "News",
      "scheme": null,
      "label": null
    }
  ],
  "credit": ""
}