{
  "news_paper": "AgenciaTélam",
  "section": "Política",
  "title": "Con reuniones de gabinete diarias, Milei prepara medidas y convoca a los gobernadores",
  "link": "https://www.telam.com.ar/notas/202312/649723-milei-medidas-gobernadores.html",
  "summary": "En sus segunda semana de gobierno, el Presidente recibirá a los mandatarios provinciales y enfrentará la primera movilización, ratificada tras la presentación del protocolo antipiquetes de Patricia Bullrich.",
  "published": "Sat, 16 Dec 2023 20:00:00 -0300",
  "tags": "",
  "credit": ""
}{
  "news_paper": "AgenciaTélam",
  "section": "Política",
  "title": "Con reuniones de gabinete diarias, Milei prepara medidas y convoca a los gobernadores",
  "link": "https://www.telam.com.ar/notas/202312/649723-milei-medidas-gobernadores.html",
  "summary": "En sus segunda semana de gobierno, el Presidente recibirá a los mandatarios provinciales y enfrentará la primera movilización, ratificada tras la presentación del protocolo antipiquetes de Patricia Bullrich.",
  "published": "Sat, 16 Dec 2023 20:00:00 -0300",
  "tags": "",
  "credit": ""
}