{
  "news_paper": "Clarin",
  "section": "Deportes",
  "title": "“Puro cuento”: Luana Volnovich negó el déficit en el PAMI y advirtió sobre los “planes” de Milei",
  "link": "https://www.lanacion.com.ar/politica/puro-cuento-luana-volnovich-nego-el-deficit-en-el-pami-y-advirtio-sobre-los-planes-que-persigue-nid18032024/",
  "summary": "La diputada camporista y extitular de la obra social afirmó que los cuatro años de su gestión fueron superavitarios y que el Gobierno busca justificar con sus denuncias nuevo recortes",
  "published": "Mon, 18 Mar 2024 23:07:02 +0000",
  "tags": [
    {
      "term": "Política",
      "scheme": null,
      "label": null
    }
  ],
  "credit": "Franco Fafasuli"
}