[
    {
        "news_paper": "lapoliticaonline",
        "section": " Ciudad",
        "title": "Jorge ya defini\u00f3 casi todo el gabinete, pero demora el anuncio por la tensi\u00f3n entre Macri y Milei",
        "link": "https://www.lapoliticaonline.com/ciudad/jorge-ya-definio-casi-todo-el-gabinete-pero-demora-el-anuncio-por-la-tension-entre-macri-y-milei/",
        "summary": "Contrario a la ola de recortes, Jorge sumar\u00e1 un ministerio m\u00e1s al organigrama porte\u00f1o.",
        "published": "Wed, 22 Nov 2023 21:07:25 GMT",
        "tags": "",
        "credit": ""
    },
    {
        "news_paper": "lapoliticaonline",
        "section": " Ciudad",
        "title": "Jorge ya defini\u00f3 casi todo el gabinete, pero demora el anuncio por la tensi\u00f3n entre Macri y Milei",
        "link": "https://www.lapoliticaonline.com/ciudad/jorge-ya-definio-casi-todo-el-gabinete-pero-demora-el-anuncio-por-la-tension-entre-macri-y-milei/",
        "summary": "Contrario a la ola de recortes, Jorge sumar\u00e1 un ministerio m\u00e1s al organigrama porte\u00f1o.",
        "published": "Wed, 22 Nov 2023 21:07:25 GMT",
        "tags": "",
        "credit": ""
    },
    {
        "news_paper": "lapoliticaonline",
        "section": " Ciudad",
        "title": "Jorge ya defini\u00f3 casi todo el gabinete, pero demora el anuncio por la tensi\u00f3n entre Macri y Milei",
        "link": "https://www.lapoliticaonline.com/ciudad/jorge-ya-definio-casi-todo-el-gabinete-pero-demora-el-anuncio-por-la-tension-entre-macri-y-milei/",
        "summary": "Contrario a la ola de recortes, Jorge sumar\u00e1 un ministerio m\u00e1s al organigrama porte\u00f1o.",
        "published": "Wed, 22 Nov 2023 21:07:25 GMT",
        "tags": "",
        "credit": ""
    },
    {
        "news_paper": "lapoliticaonline",
        "section": " Ciudad",
        "title": "Jorge ya defini\u00f3 casi todo el gabinete, pero demora el anuncio por la tensi\u00f3n entre Macri y Milei",
        "link": "https://www.lapoliticaonline.com/ciudad/jorge-ya-definio-casi-todo-el-gabinete-pero-demora-el-anuncio-por-la-tension-entre-macri-y-milei/",
        "summary": "Contrario a la ola de recortes, Jorge sumar\u00e1 un ministerio m\u00e1s al organigrama porte\u00f1o.",
        "published": "Wed, 22 Nov 2023 21:07:25 GMT",
        "tags": "",
        "credit": ""
    }
]