{
  "news_paper": "lapoliticaonline",
  "section": " Política",
  "title": "Milei echó Royón y al titular de la Anses: Macri y Bullrich pujan por meter los reemplazantes",
  "link": "https://www.lapoliticaonline.com/politica/milei-echo-royon-y-al-titular-de-la-anses-macri-y-bullrich-pujan-por-meter-los-reemplazantes/",
  "summary": "Fue primicia de LPO. El ex presidente quiere a María Eugenia Vidal o a Carolina Stanley. Sin agenda, Serenellini espera el regreso del Presidente para renunciar",
  "published": "Fri, 09 Feb 2024 22:50:00 GMT",
  "tags": "",
  "credit": ""
}