{
  "news_paper": "AmbitoFinanciero",
  "section": "Portada",
  "title": "Díaz Ayuso elogió a Javier Milei y acusó a Pedro Sánchez de empezar ''una guerra con el argentino''",
  "link": "https://www.ambito.com/politica/diaz-ayuso-elogio-javier-milei-y-acuso-pedro-sanchez-empezar-una-guerra-el-argentino-n6018763",
  "summary": "<p class=\"ignore-parser\">La funcionaria española dio una entrevista donde habló de la nueva visita de Milei a España y el conflicto con Pedro Sánchez.</p> <h2 class=\"ignore-parser\"> </h2>",
  "published": "Thu, 20 Jun 2024 20:26:00 -0300",
  "tags": "",
  "credit": ""
}