{
  "news_paper": "AmbitoFinanciero",
  "section": "Portada",
  "title": "Javier Milei adelanta viaje a España: no verá autoridades, presentará su libro y dará apoyo a ultras de Vox",
  "link": "https://www.ambito.com/politica/javier-milei-adelanta-viaje-espana-no-vera-autoridades-presentara-su-libro-y-dara-apoyo-ultras-vox-n5999451",
  "summary": "<p>El Presidente centrará la agenda en asuntos personales y partidarios antes que en cuestiones institucionales. Esquiva a Pedro Sánchez y al Rey Felipe VI.</p>",
  "published": "Thu, 16 May 2024 12:47:51 -0300",
  "tags": "",
  "credit": ""
}