{
  "news_paper": "AmbitoFinanciero",
  "section": "Portada",
  "title": "Milei, sus verdaderos soldados y el riesgo de acortar distancias con Medio Oriente",
  "link": "https://www.ambito.com/politica/milei-sus-verdaderos-soldados-y-el-riesgo-acortar-distancias-medio-oriente-n5981211",
  "summary": "<p>La novela Menem-Zago-Pagano determinó una nueva ruptura en LLA, ahora en la Cámara de Diputados. ¿Por qué se alejan los libertarios de la primera hora? El conflicto Irán-Israel y los indeseables (y temidos) fantasmas de los noventa.</p>",
  "published": "Sun, 14 Apr 2024 00:00:00 -0300",
  "tags": "",
  "credit": ""
}