{
  "news_paper": "AmbitoFinanciero",
  "section": "Últimasnoticias",
  "title": "Nicolás Dujovne le sugirió a Javier Milei subir la edad jubilatoria a 68 años",
  "link": "https://www.ambito.com/economia/exministro-le-sugirio-javier-milei-subir-la-edad-jubilatoria-68-anos-n5989236",
  "summary": "<p>''Si no lo hacemos, nos vamos a un gasto de 14 puntos del PBI en diez años\", explicó Nicolás Dujovne en su sugerencia a Javier Milei.</p>",
  "published": "Sat, 27 Apr 2024 17:57:00 -0300",
  "tags": "",
  "credit": ""
}